{"torrents_count":379334,
"limit":10,
"page":11,
"torrents":
[{"id":1585188,
"torrent_url":"magnet:?xt=urn:btih:F3095EA710F54C851C9A287195219F234F1C1214&dn=enrolados_2010_720p_brrip_mp4_by_tofushoyu&tr=udp%3a%2f%2ftracker.openbittorrent.com%3a80&tr=udp%3a%2f%2ftracker.publicbt.com%3a80&tr=udp%3a%2f%2ftracker.istole.it%3a6969&tr=udp%3a%2f%2ftracker.ccc.de%3a80&tr=udp%3a%2f%2fopen.demonii.com%3a1337",
"title":"Enrolados (2010) Dublado torrent ZMOD",
"small_screenshot":"//img.imirante.com.br/2020/02/17/1581953432-227712085-810x471.jpg",
"seeds":10,
"peers":15,
"date_released_unix":1611264309,
"size_bytes":""},

{"id":1585187,
"torrent_url":"magnet:?xt=urn:btih:814E1F23C0C3270A25FBE20EE5D771652482FDB4&dn=%5bWWW.BLUDV.TV%5d%20WiFi%20Ralph%20-%20Quebrando%20a%20Internet%202019%20%28720p%29%20%5bDUBLADO%5d%20Acesse%20o%20ORIGINAL%20WWW.BLUDV.TV&tr=udp%3a%2f%2ftracker.openbittorrent.com%3a80%2fannounce&tr=udp%3a%2f%2ftracker.opentrackr.org%3a1337%2fannounce&tr=udp%3a%2f%2f9.rarbg.to%3a2710%2fannounce&tr=udp%3a%2f%2fexplodie.org%3a6969%2fannounce&tr=http%3a%2f%2fglotorrents.pw%3a80%2fannounce&tr=udp%3a%2f%2fp4p.arenabg.com%3a1337%2fannounce&tr=udp%3a%2f%2ftorrent.gresille.org%3a80%2fannounce&tr=udp%3a%2f%2ftracker.aletorrenty.pl%3a2710%2fannounce&tr=udp%3a%2f%2ftracker.coppersurfer.tk%3a6969%2fannounce&tr=udp%3a%2f%2ftracker.piratepublic.com%3a1337%2fannounce",
"title":"WiFi Ralph: Quebrando a Internet (2019) Dublado torrent ZMOD",
"small_screenshot":"//www.artscommented.com/wp-content/uploads/2018/11/Ralph-Breaks-the-internet-1-1024x770.jpeg",
"seeds":11,
"peers":3,
"date_released_unix":1611262280,
"size_bytes":""},

{"id":1585186,
"torrent_url":"magnet:?xt=urn:btih:c845bb90d0d86b3afcfc3f6104d3a7f5d1c22eb2&dn=COMANDO.TO%20-%20Trolls.2.2020.720p.DUAL&tr=udp%3a%2f%2ftracker.openbittorrent.com",
"title":"Trolls 2  (2021) Dublado torrent ZMOD",
"small_screenshot":"//fundacaoschmidt.org.br/wp-content/uploads/2020-05-06-trolls-2-fat-alto-em-streaming-univ-e-exib-capa.jpg",
"seeds":11,
"peers":3,
"date_released_unix":1611261350,
"size_bytes":""},

{"id":1585185,
"torrent_url":"magnet:?xt=urn:btih:6DED4E2E9D1458617C192D88B08B8FDA8D9ED1B9&dn=Mulan%20O%20Filme%20(2020)%20DUAL%20%26Aacute%3BUDIO%20720p%20AlienVolt&tr=udp%3A%2F%2Ftracker.coppersurfer.tk%3A6969%2Fannounce&tr=udp%3A%2F%2F9.rarbg.to%3A2920%2Fannounce&tr=udp%3A%2F%2Ftracker.opentrackr.org%3A1337&tr=udp%3A%2F%2Ftracker.internetwarriors.net",
"title":"Mulan O Filme (2020) Dublado torrent ZMOD",
"small_screenshot":"//i.ytimg.com/vi/_QzaXvzEysk/hqdefault.jpg",
"seeds":8,"peers":1,"date_released_unix":1611260948,
"size_bytes":""},

{"id":1585184,
"torrent_url":"magnet:?xt=urn:btih:849009666A1F7A842A0488CE87965BF116557F0A&dn=Os%20Croods%202013%20Dublado%20BDRip%20720p%20-%20MHDS&tr=udp%3A%2F%2Ftracker.coppersurfer.tk%3A6969%2Fannounce&tr=udp%3A%2F%2F9.rarbg.to%3A2920%2Fannounce&tr=udp%3A%2F%2Ftracker.opentrackr.org%3A1337&tr=udp%3A%2F%2Ftracker.internetwarriors.net%3A1337%2Fannounce&tr=udp%3A%2F%2Ftracker.leechers-paradise.org%3A6969%2Fannounce&tr=udp%3A%2F%2Ftracker.coppersurfer.tk%3A6969%2Fannounce&tr=udp%3A%2F%2Ftracker.pirateparty.gr%3A6969%2Fannounce&tr=udp%3A%2F%2Ftracker.cyberia.is%3A6969%2Fannounce",
"title":"Os Croods (2013) Dublado torrent ZMOD",
"small_screenshot":"//images.hungama.com/c/1/f92/38c/49236674/49236674_1280x800.jpg",
"seeds":8,
"peers":3,
"date_released_unix":1611260729,
"size_bytes":""},

{"id":1585183,
"torrent_url":"magnet:?xt=urn:btih:dd9de23491b6af01e9246b8005540b6891090be6&dn=COMANDO.TO%20-%20Dois%20Irmaos%20-%20Uma%20Jornada%20Fantastica%202020%20%5b720p%5d%20%5bDUAL%5d&tr=udp%3a%2f%2ftracker.openbittorrent.com",
"title":"Onward (Dual audio) torrent ZMOD",
"imdb_id":"0320037",
"season":"0",
"episode":"0",
"small_screenshot":"//prod-ripcut-delivery.disney-plus.net/v1/variant/disney/81800B0CB91FDB8C9C66D67EAD554F986043DCCE1B1F3299AF96E0A6CAA7827A/scale?width=1200&aspectRatio=1.78&format=jpeg",
"seeds":11,
"peers":1,
"date_released_unix":1611260706,
"size_bytes":"230460174"},

{"id":1585182,
"torrent_url":"magnet:?xt=urn:btih:7666ae5568ac6eb440842d673d6b333243dce47e&dn=COMOEUBAIXO.COM..WEB-DL.MKV.-DUBLADO-DUAL-AUDIO-..COMANDO.TO%20-%20Soul.2020.1080p.FULL&tr=udp%3a%2f%2ftracker.openbittorrent.com",
"title":"Soul (Dual audio) torrent ZMOD",
"small_screenshot":"//maratonandopop.com.br/wp-content/uploads/2020/12/soul-directo-disney-plus-fecha_0_0_1200_747.jpg",
"seeds":10,
"peers":4,
"date_released_unix":1611260449,
"size_bytes":"125013002"},

{"id":1585181,
"torrent_url":"magnet:?xt=urn:btih:53C22DEDDE6B9850F80A5A5E3C8432639E5809C1&dn=Frozen%3A%20Uma%20Aventura%20Congelante%20(2013)%20BDRip%20720p%20Dublado%20ToTTi9&tr=udp%3A%2F%2Ftracker.coppersurfer.tk%3A6969%2Fannounce&tr=udp%3A%2F%2F9.rarbg.to%3A2920%2Fannounce&tr=udp%3A%2F%2Ftracker.opentrackr.org%3A1337&tr=udp%3A%2F%2Ftracker.internetwarriors.net",
"title":"Frozen: Uma Aventura Congelante (2013) Dublado torrent ZMOD",
"small_screenshot":"//www.sindicatometal.org.br/wp-content/uploads/2016/07/Frozen-Elsa-disney-princess-37732282-1600-900-e1468862315711-860x450_c.png",
"seeds":15,
"peers":3,
"date_released_unix":1611259984,
"size_bytes":"828145401"},

{"id":1585180,
"torrent_url":"magnet:?xt=urn:btih:5D65CF487E9AE99003A8A7AF6556AFCEC4BFBFD9&dn=%5bWWW.BLUDV.TV%5d%20Pok%c3%a9mon%20-%20Detetive%20Pikachu%202019%20%28720p%29%20%5bDUBLADO%5d%20Acesse%20o%20ORIGINAL%20WWW.BLUDV.TV&tr=udp%3a%2f%2ftracker.openbittorrent.com%3a80%2fannounce&tr=udp%3a%2f%2ftracker.opentrackr.org%3a1337%2fannounce&tr=udp%3a%2f%2f9.rarbg.to%3a2740%2fannounce&tr=udp%3a%2f%2fexplodie.org%3a6969%2fannounce&tr=http%3a%2f%2fglotorrents.pw%3a80%2fannounce&tr=udp%3a%2f%2fp4p.arenabg.com%3a1337%2fannounce&tr=udp%3a%2f%2ftorrent.gresille.org%3a80%2fannounce&tr=udp%3a%2f%2ftracker.aletorrenty.pl%3a2710%2fannounce&tr=udp%3a%2f%2ftracker.coppersurfer.tk%3a6969%2fannounce&tr=udp%3a%2f%2ftracker.piratepublic.com%3a1337%2fannounce","title":"Pokémon - Detetive Pikachu (2019) Dublado torrent ZMOD",
"small_screenshot":"//gramaturaalta.com.br/wp-content/uploads/2019/09/detetivepicachu-1140x661.jpg",
"seeds":29,
"peers":10,
"date_released_unix":1611258200,
"size_bytes":"3090395031"},

{"id":1585179,
"torrent_url":"magnet:?xt=urn:btih:7b32c3e984b7baa86aed2cbcecb024e898d2c2e4&dn=LAPUMiA.Org%20-%20Frozen%202%202020%205.1%20(720p-Mp4)&tr=udp%3a%2f%2ftracker.opentrackr.org%3a1337%2fannounce&tr=udp%3a%2f%2ftracker.openbittorrent.com%3a80%2fannounce&tr=udp%3a%2f%2ftracker.trackerfix.com%3a80%2fannounce&tr=udp%3a%2f%2ftracker.coppersurfer.tk%3a6969%2fannounce&tr=udp%3a%2f%2ftracker.leechers-paradise.org%3a6969%2fannounce&tr=udp%3a%2f%2feddie4.nl%3a6969%2fannounce&tr=udp%3a%2f%2fp4p.arenabg.com%3a1337%2fannounce&tr=udp%3a%2f%2fexplodie.org%3a6969%2fannounce&tr=udp%3a%2f%2fzer0day.ch%3a1337%2fannounce",
"title":"Frozen 2 : (2019) Dublado torrent ZMOD",
"small_screenshot":"//i2.wp.com/noticiasetecnologia.com/wp-content/uploads/2020/09/Frozen-2-2.jpg",
"seeds":13,
"peers":6,
"date_released_unix":1611258016,
"size_bytes":"1389138045"}]}





